{
  "stories": [
    {
      "name": "Konnor",
      "route": "/chat",
      "src": "/images/200x200.png"
    },
    {
      "name": "Travis",
      "route": "/chat",
      "src": "/images/200x200.png"
    },
    {
      "name": "Fuller",
      "route": "/chat",
      "src": "/images/200x200.png"
    },
    {
      "name": "Alfredo",
      "route": "/chat",
      "src": "/images/200x200.png"
    },
    {
      "name": "Elliott",
      "route": "/chat",
      "src": "/images/200x200.png"
    },
    {
      "name": "Derrick",
      "route": "/chat",
      "src": "/images/200x200.png"
    },
    {
      "name": "Simmons",
      "route": "/chat",
      "src": "/images/200x200.png"
    },
    {
      "name": "Katrina",
      "route": "/chat",
      "src": "/images/200x200.png"
    },
    {
      "name": "Henry",
      "route": "/chat",
      "src": "/images/200x200.png"
    },
    {
      "name": "Curtis",
      "route": "/chat",
      "src": "/images/200x200.png"
    },
    {
      "name": "Samantha",
      "route": "/chat",
      "src": "/images/200x200.png"
    },
    {
      "name": "Corey",
      "route": "/chat",
      "src": "/images/200x200.png"
    },
    {
      "name": "Lance",
      "route": "/chat",
      "src": "/images/200x200.png"
    },
    {
      "name": "Tucker",
      "route": "/chat",
      "src": "/images/200x200.png"
    },
    {
      "name": "Jensen",
      "route": "/chat",
      "src": "/images/200x200.png"
    },
    {
      "name": "Perkins",
      "route": "/chat",
      "src": "/images/200x200.png"
    },
    {
      "name": "Evans",
      "route": "/chat",
      "src": "/images/200x200.png"
    }
  ]
}